llmplus/Manual.py
llmplus/PowerAutomate.py
llmplus/ChatGot/Models.py
llmplus/ChatGot/api.py
llmplus-0.2.1.dist-info/LICENSE
llmplus-0.2.1.dist-info/METADATA
llmplus-0.2.1.dist-info/WHEEL
llmplus-0.2.1.dist-info/top_level.txt
llmplus-0.2.1.dist-info/RECORD
