Metadata-Version: 2.1
Name: llmplus
Version: 0.2.1
Summary: A package for using llm models with api
Author-email: Amirmahdi Mohammadi <mohamadi.mahdi.6@gmail.com>
Project-URL: Homepage, https://github.com/am-mohammadi/llmplus
Classifier: Programming Language :: Python :: 3
Classifier: License :: OSI Approved :: MIT License
Classifier: Operating System :: OS Independent
Requires-Python: >=3.7
License-File: LICENSE
